plsnocrash/__init__.py
plsnocrash/plsnocrash.py
plsnocrash-0.1.3.dist-info/LICENSE
plsnocrash-0.1.3.dist-info/METADATA
plsnocrash-0.1.3.dist-info/WHEEL
plsnocrash-0.1.3.dist-info/top_level.txt
plsnocrash-0.1.3.dist-info/RECORD
