Metadata-Version: 2.1
Name: plsnocrash
Version: 0.1.3
Summary: Ever had your code crash after 10 hours of heavy computation because of a dumb mistake?
Home-page: https://github.com/HenryWConklin/plsnocrash
Author: Henry Conklin
Author-email: henrywconklin@gmail.com
License: UNKNOWN
Platform: UNKNOWN
